MANIFEST.in
README.md
setup.py
test_vacumm_data.py
vacumm_data.py
etc/modulefiles/vacumm-data
share/vacumm/samples/ETOPO2v2g_flt.grd
share/vacumm/samples/SectionG_simplified.mat
share/vacumm/samples/celtic_sea.xyz
share/vacumm/samples/data.misc.profile.nc
share/vacumm/samples/logo_ifremer.png
share/vacumm/samples/mars2d.xyt.2008081500.nc
share/vacumm/samples/mars2d.xyt.2008081508.nc
share/vacumm/samples/mars2d.xyt.2008081516.nc
share/vacumm/samples/mars2d.xyt.nc
share/vacumm/samples/mars3d.botop.20130421T0000Z.nc
share/vacumm/samples/mars3d.botop.20130421T1200Z.nc
share/vacumm/samples/mars3d.t.nc
share/vacumm/samples/mars3d.tsigyx.nc
share/vacumm/samples/mars3d.x.uv.nc
share/vacumm/samples/mars3d.xt.xe.nc
share/vacumm/samples/mars3d.xy.nc
share/vacumm/samples/mars3d.xz.nc
share/vacumm/samples/menor.nc
share/vacumm/samples/mfs.nc
share/vacumm/samples/mpi.nc
share/vacumm/samples/mpi.txt
share/vacumm/samples/nobounds.nc
share/vacumm/samples/radial_speed.nc
share/vacumm/samples/swan.four.nc
share/vacumm/samples/tide.sealevel.BREST.mars.nc
share/vacumm/samples/uv_pacific.nc
share/vacumm/samples/wrf_1d.nc
share/vacumm/samples/wrf_2d.nc
share/vacumm/samples/ne_110m_land/ne_110m_land.README.html
share/vacumm/samples/ne_110m_land/ne_110m_land.VERSION.txt
share/vacumm/samples/ne_110m_land/ne_110m_land.dbf
share/vacumm/samples/ne_110m_land/ne_110m_land.prj
share/vacumm/samples/ne_110m_land/ne_110m_land.shp
share/vacumm/samples/ne_110m_land/ne_110m_land.shx
share/vacumm/sea_level/niv_moy.txt
share/vacumm/sea_level/ports.txt
share/vacumm/shorelines/GSHHS/gshhs_land.dbf
share/vacumm/shorelines/GSHHS/gshhs_land.prj
share/vacumm/shorelines/GSHHS/gshhs_land.sbn
share/vacumm/shorelines/GSHHS/gshhs_land.sbx
share/vacumm/shorelines/GSHHS/gshhs_land.shp.xml
share/vacumm/shorelines/GSHHS/gshhs_land.shx
share/vacumm/shorelines/TCHistolitt-V1-0-RGF93-polygone/TCHistolitt-V1-0-RGF93-polygone.dbf
share/vacumm/shorelines/TCHistolitt-V1-0-RGF93-polygone/TCHistolitt-V1-0-RGF93-polygone.prj
vacumm_data.egg-info/PKG-INFO
vacumm_data.egg-info/SOURCES.txt
vacumm_data.egg-info/dependency_links.txt
vacumm_data.egg-info/top_level.txt