Metadata-Version: 1.1
Name: vacumm-data
Version: 1.2.0
Summary: Data used by the vacumm python library and its tutorials and tests
Home-page: https://www.ifremer.fr/vacumm
Author: Stephane Raynaud
Author-email: stephane.raynaud@gmail.com
License: UNKNOWN
Platform: UNKNOWN
Classifier: Intended Audience :: Science/Research
Classifier: License :: OSI Approved :: CEA CNRS Inria Logiciel Libre License, version 2.1 (CeCILL-2.1)
Classifier: Programming Language :: Python :: 2
Classifier: Programming Language :: Python :: 3
Classifier: Operating System :: OS Independent
